odoo8_addon_hr_family-8.0.1.3.0-py2.7-nspkg.pth
odoo8_addon_hr_family-8.0.1.3.0.dist-info/DESCRIPTION.rst
odoo8_addon_hr_family-8.0.1.3.0.dist-info/METADATA
odoo8_addon_hr_family-8.0.1.3.0.dist-info/RECORD
odoo8_addon_hr_family-8.0.1.3.0.dist-info/WHEEL
odoo8_addon_hr_family-8.0.1.3.0.dist-info/metadata.json
odoo8_addon_hr_family-8.0.1.3.0.dist-info/namespace_packages.txt
odoo8_addon_hr_family-8.0.1.3.0.dist-info/top_level.txt
odoo_addons/hr_family/README.rst
odoo_addons/hr_family/__init__.py
odoo_addons/hr_family/__openerp__.py
odoo_addons/hr_family/hooks.py
odoo_addons/hr_family/data/hr_employee_marital_status.xml
odoo_addons/hr_family/data/hr_employee_spouse_data.xml
odoo_addons/hr_family/demo/hr_employee.xml
odoo_addons/hr_family/i18n/am.po
odoo_addons/hr_family/i18n/ar.po
odoo_addons/hr_family/i18n/bg.po
odoo_addons/hr_family/i18n/bs.po
odoo_addons/hr_family/i18n/ca.po
odoo_addons/hr_family/i18n/cs.po
odoo_addons/hr_family/i18n/da.po
odoo_addons/hr_family/i18n/de.po
odoo_addons/hr_family/i18n/el_GR.po
odoo_addons/hr_family/i18n/en_GB.po
odoo_addons/hr_family/i18n/es.po
odoo_addons/hr_family/i18n/es_AR.po
odoo_addons/hr_family/i18n/es_CL.po
odoo_addons/hr_family/i18n/es_CO.po
odoo_addons/hr_family/i18n/es_CR.po
odoo_addons/hr_family/i18n/es_DO.po
odoo_addons/hr_family/i18n/es_EC.po
odoo_addons/hr_family/i18n/es_ES.po
odoo_addons/hr_family/i18n/es_MX.po
odoo_addons/hr_family/i18n/es_PE.po
odoo_addons/hr_family/i18n/es_PY.po
odoo_addons/hr_family/i18n/es_VE.po
odoo_addons/hr_family/i18n/et.po
odoo_addons/hr_family/i18n/fa.po
odoo_addons/hr_family/i18n/fi.po
odoo_addons/hr_family/i18n/fr.po
odoo_addons/hr_family/i18n/fr_CA.po
odoo_addons/hr_family/i18n/fr_CH.po
odoo_addons/hr_family/i18n/gl.po
odoo_addons/hr_family/i18n/gl_ES.po
odoo_addons/hr_family/i18n/he.po
odoo_addons/hr_family/i18n/hr.po
odoo_addons/hr_family/i18n/hr_HR.po
odoo_addons/hr_family/i18n/hu.po
odoo_addons/hr_family/i18n/id.po
odoo_addons/hr_family/i18n/it.po
odoo_addons/hr_family/i18n/ja.po
odoo_addons/hr_family/i18n/ko.po
odoo_addons/hr_family/i18n/lt.po
odoo_addons/hr_family/i18n/lt_LT.po
odoo_addons/hr_family/i18n/lv.po
odoo_addons/hr_family/i18n/mk.po
odoo_addons/hr_family/i18n/mn.po
odoo_addons/hr_family/i18n/nb.po
odoo_addons/hr_family/i18n/nb_NO.po
odoo_addons/hr_family/i18n/nl.po
