Metadata-Version: 2.0
Name: odoo8-addon-hr-family
Version: 8.0.1.3.0
Summary: Employee Family information tab
Home-page: http://www.openerp.com
Author: Michael Telahun Makonnen <mmakonnen@gmail.com>,Therp BV,Odoo Community Association (OCA)
Author-email: support@odoo-community.org
License: AGPL-3
Platform: UNKNOWN
Classifier: Programming Language :: Python
Classifier: Framework :: Odoo
Classifier: License :: OSI Approved :: GNU Affero General Public License v3
Requires-Python: ~=2.7
Requires-Dist: odoo (<9.0a,>=8.0a)
